medpicpy/__init__.py
medpicpy/config.py
medpicpy/io.py
medpicpy/parsing.py
medpicpy/paths.py
medpicpy/utils.py
medpicpy-1.0.4.dist-info/LICENSE
medpicpy-1.0.4.dist-info/METADATA
medpicpy-1.0.4.dist-info/WHEEL
medpicpy-1.0.4.dist-info/top_level.txt
medpicpy-1.0.4.dist-info/RECORD
