Metadata-Version: 2.1
Name: medpicpy
Version: 1.0.4
Summary: A package to simplify loading medical imaging datasets.
Home-page: https://github.com/cdmacfadyen/medpicpy
Author: Craig Macfadyen
Author-email: cdmacfadyen@gmail.com
License: MIT
Keywords: medical-imaging,python,computer-vision,machine-learning
Platform: UNKNOWN
Classifier: Development Status :: 5 - Production/Stable
Classifier: Intended Audience :: Developers
Classifier: License :: OSI Approved :: MIT License
Classifier: Programming Language :: Python :: 3
Requires-Dist: Mako
Requires-Dist: Markdown
Requires-Dist: MarkupSafe
Requires-Dist: Pillow
Requires-Dist: SimpleITK
Requires-Dist: cycler
Requires-Dist: importlib-metadata
Requires-Dist: kiwisolver
Requires-Dist: matplotlib
Requires-Dist: numpy
Requires-Dist: opencv-python
Requires-Dist: pandas
Requires-Dist: pdoc3
Requires-Dist: pyparsing
Requires-Dist: python-dateutil
Requires-Dist: pytz
Requires-Dist: six
Requires-Dist: zipp
